blocks_builder/__init__.py
blocks_builder/builder.py
blocks_builder/generate_files.py
blocks_builder/version.py
blocks_builder/blocks/__init__.py
blocks_builder/blocks/actions.py
blocks_builder/blocks/context.py
blocks_builder/blocks/divider.py
blocks_builder/blocks/header.py
blocks_builder/blocks/image.py
blocks_builder/blocks/input.py
blocks_builder/blocks/section.py
blocks_builder/blocks/base_elements/__init__.py
blocks_builder/blocks/base_elements/input_base_elements.py
blocks_builder/blocks/base_elements/section_base_elements.py
blocks_builder/blocks/core/__init__.py
blocks_builder/blocks/core/base_blocks.py
blocks_builder/blocks/core/select.py
blocks_builder/blocks/core/text.py
blocks_builder/maps/__init__.py
blocks_builder/maps/action_map.py
blocks_builder/maps/input_map.py
blocks_builder/maps/section_map.py
blocks_builder/utils/__init__.py
blocks_builder/utils/utilities.py
slack_blocks_builder-0.1.0.dist-info/LICENSE
slack_blocks_builder-0.1.0.dist-info/METADATA
slack_blocks_builder-0.1.0.dist-info/WHEEL
slack_blocks_builder-0.1.0.dist-info/entry_points.txt
slack_blocks_builder-0.1.0.dist-info/top_level.txt
slack_blocks_builder-0.1.0.dist-info/RECORD
