Metadata-Version: 2.1
Name: slack-blocks-builder
Version: 0.1.0
Home-page: https://github.com/ABizzinotto/slack-blocks-builder
Classifier: Programming Language :: Python :: 3.10
Classifier: License :: OSI Approved :: MIT License
Classifier: Operating System :: OS Independent
Requires-Python: >=3.10
License-File: LICENSE
Requires-Dist: pydantic
Requires-Dist: pyyaml
